pyaradi/__init__.py
pyaradi/aradi.py
pyaradi/aradi_arg.py
pyaradi/aradi_core.py
pyaradi/aradi_utils.py
pyaradi-0.1.3.dist-info/LICENSE
pyaradi-0.1.3.dist-info/METADATA
pyaradi-0.1.3.dist-info/WHEEL
pyaradi-0.1.3.dist-info/entry_points.txt
pyaradi-0.1.3.dist-info/top_level.txt
pyaradi-0.1.3.dist-info/RECORD
