Metadata-Version: 2.1
Name: pyaradi
Version: 0.1.3
Summary: ARADI encryption implementation with CTR modes
Home-page: https://github.com/AndreisPurim/ARADI
Author: A. Purim, G. Praciano
Author-email: andreispurim@gmail.com
Classifier: Programming Language :: Python :: 3
Classifier: License :: OSI Approved :: MIT License
Classifier: Operating System :: OS Independent
License-File: LICENSE
Requires-Dist: pycryptodome
